moviesigdb/__init__.py
moviesigdb/core.py
moviesigdb/viz.py
moviesigdb-0.1.0.dist-info/licenses/LICENSE
moviesigdb-0.1.0.dist-info/METADATA
moviesigdb-0.1.0.dist-info/WHEEL
moviesigdb-0.1.0.dist-info/top_level.txt
moviesigdb-0.1.0.dist-info/RECORD
