Metadata-Version: 2.4
Name: moviesigdb
Version: 0.1.0
Summary: A tool to generate and analyze color barcodes from video files.
Author-email: Shreyan Banerjee <2006shreybanerjee@gmail.com>
Project-URL: Homepage, https://github.com/shreyanbruh/moviesigdb
Classifier: Programming Language :: Python :: 3
Classifier: License :: OSI Approved :: MIT License
Classifier: Operating System :: OS Independent
Requires-Python: >=3.8
License-File: LICENSE
Requires-Dist: numpy
Requires-Dist: matplotlib
Requires-Dist: opencv-python
Requires-Dist: tqdm
Dynamic: license-file
